imjoy_rpc/VERSION
imjoy_rpc/__init__.py
imjoy_rpc/qr.py
imjoy_rpc/rpc.py
imjoy_rpc/utils.py
imjoy_rpc/connection/__init__.py
imjoy_rpc/connection/colab_connection.py
imjoy_rpc/connection/imjoy_colab.html
imjoy_rpc/connection/jupyter_connection.py
imjoy_rpc/connection/pyodide_connection.py
imjoy_rpc/connection/socketio_connection.py
imjoy_rpc/core_connection/__init__.py
imjoy_rpc/hypha/__init__.py
imjoy_rpc/hypha/pyodide_sse.py
imjoy_rpc/hypha/pyodide_websocket.py
imjoy_rpc/hypha/rpc.py
imjoy_rpc/hypha/sse_client.py
imjoy_rpc/hypha/sync.py
imjoy_rpc/hypha/utils.py
imjoy_rpc/hypha/webrtc_client.py
imjoy_rpc/hypha/websocket_client.py
imjoy_rpc/werkzeug/__init__.py
imjoy_rpc/werkzeug/_compat.py
imjoy_rpc/werkzeug/local.py
tests/__init__.py
tests/conftest.py
tests/test_jupyter_rpc.py
tests/test_utils.py
tests/test_websocket_rpc.py
imjoy_rpc-0.5.59.dist-info/METADATA
imjoy_rpc-0.5.59.dist-info/WHEEL
imjoy_rpc-0.5.59.dist-info/top_level.txt
imjoy_rpc-0.5.59.dist-info/RECORD
