Metadata-Version: 2.1
Name: imjoy-rpc
Version: 0.5.59
Summary: ImJoy Plugin Engine for running Python plugins locally or remotely from ImJoy.io
Home-page: http://github.com/imjoy-team/imjoy-rpc
Author: ImJoy Team
Author-email: imjoy.team@gmail.com
License: MIT
Platform: UNKNOWN
Requires-Python: >=3.6
Requires-Dist: msgpack >=1.0.2
Requires-Dist: shortuuid >=1.0.8
Requires-Dist: websockets ; platform_system != "Emscripten"
Requires-Dist: aiocontextvars ; python_version < "3.7"
Requires-Dist: contextvars ; python_version < "3.7"
Provides-Extra: full
Requires-Dist: numpy ; extra == 'full'
Requires-Dist: python-engineio >=4.1.0 ; extra == 'full'
Requires-Dist: python-socketio[client] >=5.4.1 ; extra == 'full'
Requires-Dist: zarr ; extra == 'full'
Requires-Dist: aiortc ; (platform_system != "Emscripten") and extra == 'full'
Provides-Extra: socketio
Requires-Dist: python-engineio >=4.1.0 ; extra == 'socketio'
Requires-Dist: python-socketio[client] >=5.4.1 ; extra == 'socketio'
